mooquant_silver/__init__.py
mooquant_silver/api.py
mooquant_silver/broker.py
mooquant_silver/common.py
mooquant_silver/livefeed.py
mooquant_silver-0.1.1.dist-info/DESCRIPTION.rst
mooquant_silver-0.1.1.dist-info/METADATA
mooquant_silver-0.1.1.dist-info/RECORD
mooquant_silver-0.1.1.dist-info/WHEEL
mooquant_silver-0.1.1.dist-info/entry_points.txt
mooquant_silver-0.1.1.dist-info/metadata.json
mooquant_silver-0.1.1.dist-info/top_level.txt
