Metadata-Version: 2.0
Name: mooquant-silver
Version: 0.1.1
Summary: mooquant bitfinex module
Home-page: https://github.com/bopo/mooquant_silver
Author: bopo.wang
Author-email: ibopo@126.com
License: MIT license
Keywords: mooquant_silver
Platform: UNKNOWN
Classifier: Development Status :: 2 - Pre-Alpha
Classifier: Intended Audience :: Developers
Classifier: License :: OSI Approved :: MIT License
Classifier: Natural Language :: English
Classifier: Programming Language :: Python :: 3
Classifier: Programming Language :: Python :: 3.3
Classifier: Programming Language :: Python :: 3.4
Classifier: Programming Language :: Python :: 3.5
Requires-Dist: mooquant
